{
  "project_info": {
    "project_number": "51211642823",
    "project_id": "minerva-3510c",
    "storage_bucket": "minerva-3510c.firebasestorage.app"
  },
  "client": [
    {
      "client_info": {
        "mobilesdk_app_id": "1:51211642823:android:3e25594bb2ce6cd3ccdbe2",
        "android_client_info": {
          "package_name": "nl.minerva.clubapp.v2"
        }
      },
      "oauth_client": [],
      "api_key": [
        {
          "current_key": "AIzaSyAyDek_d5rbBwXVWWwFaAUF7TTSLZ_Dkpc"
        }
      ],
      "services": {
        "appinvite_service": {
          "other_platform_oauth_client": []
        }
      }
    }
  ],
  "configuration_version": "1"
}